fundamental_gen/__init__.py
fundamental_gen-0.0.3.dist-info/METADATA
fundamental_gen-0.0.3.dist-info/WHEEL
fundamental_gen-0.0.3.dist-info/licenses/LICENSE
fundamental_gen-0.0.3.dist-info/RECORD
