Metadata-Version: 2.1
Name: fundamental_gen
Version: 0.0.3
Summary: Fundamental genarator
Project-URL: Homepage, https://github.com/tienvuong-vn/yahoofinancials
Project-URL: Bug Tracker, https://github.com/tienvuong-vn/yahoofinancials
Author-email: Vuong Nguyen <tienvuong.gt@gmail.com>
License: MIT License
Classifier: License :: OSI Approved :: MIT License
Classifier: Operating System :: OS Independent
Classifier: Programming Language :: Python :: 3
Requires-Python: >=3.7
